light_ai/.DS_Store
light_ai/__init__.py
light_ai/agent.py
light_ai/core/base.py
light_ai/core/config.py
light_ai/core/memory.py
light_ai/core/messages.py
light_ai/graphs/__init__.py
light_ai/graphs/graph.py
light_ai/graphs/graph_agent.py
light_ai/llms/__init__.py
light_ai/llms/google.py
ailight_agents-0.1.6.dist-info/METADATA
ailight_agents-0.1.6.dist-info/WHEEL
ailight_agents-0.1.6.dist-info/RECORD
