Metadata-Version: 2.1
Name: ailight-agents
Version: 0.1.6
Summary: 
Author: alessandropolverino
Author-email: alessandropolverino01@gmail.com
Requires-Python: >=3.11,<4.0
Classifier: Programming Language :: Python :: 3
Classifier: Programming Language :: Python :: 3.11
Classifier: Programming Language :: Python :: 3.12
Provides-Extra: all
Provides-Extra: google
Requires-Dist: google-genai (>=1.21.1,<2.0.0) ; extra == "google" or extra == "all"
